README
setup.py
imglib/__init__.py
imglib/imgcomparison.py
imglib.egg-info/PKG-INFO
imglib.egg-info/SOURCES.txt
imglib.egg-info/dependency_links.txt
imglib.egg-info/top_level.txt
tests/__init__.py