Metadata-Version: 1.1
Name: imglib
Version: 1.5
Summary: search a sub image from a parent image
Home-page: UNKNOWN
Author: baohongbin
Author-email: hongbin.bao@gmail.com
License: MIT
Keywords: python opencv binding to search sub image
Platform: Linux
Classifier: Development Status :: 3 - Alpha
